MANIFEST.in
README.rst
setup.py
CosmoBolognaLib/Instructions.txt
CosmoBolognaLib/Makefile
CosmoBolognaLib/libCAT.so
CosmoBolognaLib/libCBL.so
CosmoBolognaLib/libCM.so
CosmoBolognaLib/libCOSM.so
CosmoBolognaLib/libDATA.so
CosmoBolognaLib/libDISTR.so
CosmoBolognaLib/libFFT.so
CosmoBolognaLib/libFIELD.so
CosmoBolognaLib/libFUNC.so
CosmoBolognaLib/libFUNCGRID.so
CosmoBolognaLib/libGLOB.so
CosmoBolognaLib/libHIST.so
CosmoBolognaLib/libKERNEL.so
CosmoBolognaLib/libLN.so
CosmoBolognaLib/libMODEL_COSM.so
CosmoBolognaLib/libMODEL_GLOB.so
CosmoBolognaLib/libMODEL_NC.so
CosmoBolognaLib/libMODEL_THREEP.so
CosmoBolognaLib/libMODEL_TWOP.so
CosmoBolognaLib/libNC.so
CosmoBolognaLib/libRAN.so
CosmoBolognaLib/libREADP.so
CosmoBolognaLib/libSTAT.so
CosmoBolognaLib/libTHREEP.so
CosmoBolognaLib/libTWOP.so
CosmoBolognaLib/libWRAP.so
CosmoBolognaLib/test.py
CosmoBolognaLib.egg-info/PKG-INFO
CosmoBolognaLib.egg-info/SOURCES.txt
CosmoBolognaLib.egg-info/dependency_links.txt
CosmoBolognaLib.egg-info/not-zip-safe
CosmoBolognaLib.egg-info/top_level.txt
CosmoBolognaLib/Catalogue/Catalogue.cpp
CosmoBolognaLib/Catalogue/Catalogue.o
CosmoBolognaLib/Catalogue/ChainMesh_Catalogue.cpp
CosmoBolognaLib/Catalogue/ChainMesh_Catalogue.o
CosmoBolognaLib/Catalogue/FITSCatalogue.cpp
CosmoBolognaLib/Catalogue/FITSCatalogue.o
CosmoBolognaLib/Catalogue/GadgetCatalogue.cpp
CosmoBolognaLib/Catalogue/GadgetCatalogue.o
CosmoBolognaLib/Catalogue/Object.cpp
CosmoBolognaLib/Catalogue/Object.o
CosmoBolognaLib/Catalogue/RandomCatalogue.cpp
CosmoBolognaLib/Catalogue/RandomCatalogue.o
CosmoBolognaLib/Catalogue/RandomCatalogueVIPERS.cpp
CosmoBolognaLib/Catalogue/RandomCatalogueVIPERS.o
CosmoBolognaLib/Catalogue/VoidCatalogue.cpp
CosmoBolognaLib/Catalogue/VoidCatalogue.o
CosmoBolognaLib/Catalogue/em
CosmoBolognaLib/Catalogue/vm
CosmoBolognaLib/ChainMesh/ChainMesh.cpp
CosmoBolognaLib/ChainMesh/ChainMesh.o
CosmoBolognaLib/ChainMesh/em
CosmoBolognaLib/ChainMesh/vm
CosmoBolognaLib/Cosmology/Lib/3PCF.cpp
CosmoBolognaLib/Cosmology/Lib/3PCF.o
CosmoBolognaLib/Cosmology/Lib/BAO.cpp
CosmoBolognaLib/Cosmology/Lib/BAO.o
CosmoBolognaLib/Cosmology/Lib/Bias.cpp
CosmoBolognaLib/Cosmology/Lib/Bias.o
