Metadata-Version: 1.0
Name: CosmoBolognaLib
Version: 5.2
Summary: C++ libraries for cosmological calculations
Home-page: http://github.com/federicomarulli/CosmoBolognaLib
Author: Federico Marulli
Author-email: federico.marulli3@unibo.it
License: GNU General Public License
Platform: UNKNOWN
